{
    "prevs_minimo": "1.332.772.180,79 reais (2025-09)",
    "prevs_maximo": "1.679.258.632,36 reais (2026-02)",
    "prevs_media": "1.611.440.263,13 reais",
    "prevs_soma": "19.337.283.157,55 reais",
    "prevs_mediana": "1.657.382.555,76 reais",
    "prevs_desvioPadrao": "102.630.563,20 reais",
    "prevs_mediaUltimos12m": "1.486.923.313,00 reais",
    "prevs_somaUltimos12m": "17.843.079.756,00 reais",
    "prevs_crescimentoPercentualPrevisto": "+8.37%",
    "periodo_treinamento": "2014-03 a 2025-08 (138 meses)",
    "periodo_previsoes": "2025-09 a 2026-08 (12 meses)"
}