{
    "prevs_minimo": "275.692,18 reais (2026-04)",
    "prevs_maximo": "363.110,63 reais (2026-06)",
    "prevs_media": "308.477,50 reais",
    "prevs_soma": "3.701.730,00 reais",
    "prevs_mediana": "296.553,46 reais",
    "prevs_desvioPadrao": "25.606,37 reais",
    "prevs_mediaUltimos12m": "269.098,20 reais",
    "prevs_somaUltimos12m": "3.229.178,37 reais",
    "prevs_crescimentoPercentualPrevisto": "+14.63%",
    "periodo_treinamento": "2014-03 a 2025-08 (138 meses)",
    "periodo_previsoes": "2025-09 a 2026-08 (12 meses)"
}