{
    "prevs_minimo": "114.935.370,14 reais (2026-02)",
    "prevs_maximo": "184.219.770,02 reais (2025-12)",
    "prevs_media": "123.859.593,43 reais",
    "prevs_somaProx12meses": "1.486.315.121,10 reais",
    "prevs_mediana": "118.683.778,13 reais",
    "prevs_desvioPadrao": "18.503.255,50 reais",
    "prevs_mediaUltimos12m": "129065873.67 reais",
    "prevs_mediaPrevistaForaDaAmostra": "123859593.43 reais",
    "prevs_crescimentoPercentualPrevisto": "-4.03%",
    "periodo_treinamento": "2014-03 a 2025-08 (138 meses)",
    "periodo_previsoes": "2025-09 a 2026-08 (12 meses)"
}