{
    "prevs_minimo": "2.547.578.159,51 reais (2026-03)",
    "prevs_maximo": "2.698.686.793,20 reais (2025-12)",
    "prevs_media": "2.636.288.745,04 reais",
    "prevs_soma": "31.635.464.940,44 reais",
    "prevs_mediana": "2.654.763.514,57 reais",
    "prevs_desvioPadrao": "49.504.150,00 reais",
    "prevs_mediaUltimos12m": "2.332.598.604,92 reais",
    "prevs_somaUltimos12m": "27.991.183.259,00 reais",
    "prevs_crescimentoPercentualPrevisto": "+13.02%",
    "periodo_treinamento": "2014-03 a 2025-08 (138 meses)",
    "periodo_previsoes": "2025-09 a 2026-08 (12 meses)"
}