{
    "prevs_minimo": "19.548.999,85 reais (2025-10)",
    "prevs_maximo": "534.764.747,12 reais (2026-01)",
    "prevs_media": "70.051.457,90 reais",
    "prevs_soma": "840.617.494,85 reais",
    "prevs_mediana": "24.422.421,12 reais",
    "prevs_desvioPadrao": "140.448.373,04 reais",
    "prevs_mediaUltimos12m": "98.929.890,14 reais",
    "prevs_somaUltimos12m": "1.187.158.681,72 reais",
    "prevs_crescimentoPercentualPrevisto": "-29.19%",
    "periodo_treinamento": "2014-03 a 2025-08 (138 meses)",
    "periodo_previsoes": "2025-09 a 2026-08 (12 meses)"
}