{
    "prevs_minimo": "810.032.280,02 reais (2026-07)",
    "prevs_maximo": "1.287.000.946,19 reais (2026-02)",
    "prevs_media": "1.079.835.715,15 reais",
    "prevs_somaProx12meses": "12.958.028.581,82 reais",
    "prevs_mediana": "1.072.938.763,84 reais",
    "prevs_desvioPadrao": "189.680.354,10 reais",
    "prevs_mediaUltimos12m": "1018069551.25 reais",
    "prevs_mediaPrevistaForaDaAmostra": "1079835715.15 reais",
    "prevs_crescimentoPercentualPrevisto": "+6.07%",
    "periodo_treinamento": "2014-03 a 2025-08 (138 meses)",
    "periodo_previsoes": "2025-09 a 2026-08 (12 meses)"
}