{
    "prevs_minimo": "1.679.986.434,46 reais (2025-09)",
    "prevs_maximo": "2.029.808.453,49 reais (2025-12)",
    "prevs_media": "1.869.371.072,55 reais",
    "prevs_soma": "22.432.452.870,64 reais",
    "prevs_mediana": "1.885.973.504,99 reais",
    "prevs_desvioPadrao": "95.948.965,49 reais",
    "prevs_mediaUltimos12m": "1.691.560.335,83 reais",
    "prevs_somaUltimos12m": "20.298.724.030,00 reais",
    "prevs_crescimentoPercentualPrevisto": "+10.51%",
    "periodo_treinamento": "2014-03 a 2025-08 (138 meses)",
    "periodo_previsoes": "2025-09 a 2026-08 (12 meses)"
}