{
    "prevs_minimo": "3.040.089,95 reais (2026-07)",
    "prevs_maximo": "3.131.972,12 reais (2025-09)",
    "prevs_media": "3.076.769,98 reais",
    "prevs_soma": "36.921.239,75 reais",
    "prevs_mediana": "3.066.631,01 reais",
    "prevs_desvioPadrao": "27.276,48 reais",
    "prevs_mediaUltimos12m": "3.549.125,54 reais",
    "prevs_somaUltimos12m": "42.589.506,49 reais",
    "prevs_crescimentoPercentualPrevisto": "-13.31%",
    "periodo_treinamento": "2014-03 a 2025-08 (138 meses)",
    "periodo_previsoes": "2025-09 a 2026-08 (12 meses)"
}